{
  "app_key": "application.generated.unity.steamvr.exe",
  "bindings": {
    "/actions/default": {
      "chords": [],
      "poses": [
        {
          "output": "/actions/default/in/pose",
          "path": "/user/hand/left/pose/raw"
        },
        {
          "output": "/actions/default/in/pose",
          "path": "/user/hand/right/pose/raw"
        }
      ],
      "haptics": [
        {
          "output": "/actions/default/out/haptic",
          "path": "/user/hand/left/output/haptic"
        },
        {
          "output": "/actions/default/out/haptic",
          "path": "/user/hand/right/output/haptic"
        }
      ],
      "sources": [
        {
          "path": "/user/hand/left/input/trigger",
          "mode": "button",
          "parameters": {},
          "inputs": {
            "click": {
              "output": "/actions/default/in/interactui"
            }
          }
        },
        {
          "path": "/user/hand/right/input/trigger",
          "mode": "button",
          "parameters": {},
          "inputs": {
            "click": {
              "output": "/actions/default/in/interactui"
            }
          }
        },
        {
          "path": "/user/hand/left/input/pinch",
          "mode": "grab",
          "parameters": {
            "force_hold_threshold": "0.02",
            "force_release_threshold": "0.01"
          },
          "inputs": {
            "grab": {
              "output": "/actions/default/in/grabpinch"
            }
          }
        },
        {
          "path": "/user/hand/right/input/pinch",
          "mode": "grab",
          "parameters": {
            "force_hold_threshold": "0.02",
            "force_release_threshold": "0.01"
          },
          "inputs": {
            "grab": {
              "output": "/actions/default/in/grabpinch"
            }
          }
        }
      ],
      "skeleton": []
    }
  },
  "controller_type": "knuckles",
  "description": "",
  "name": "knuckles_default"
}